zodable_kotlin_primitives/__init__.py
zodable_kotlin_primitives/pair.py
zodable_kotlin_primitives/py.typed
zodable_kotlin_primitives-1.0.0.dist-info/METADATA
zodable_kotlin_primitives-1.0.0.dist-info/WHEEL
zodable_kotlin_primitives-1.0.0.dist-info/top_level.txt
zodable_kotlin_primitives-1.0.0.dist-info/RECORD
