Metadata-Version: 2.1
Name: zodable_kotlin_primitives
Version: 1.0.0
Summary: Kotlin primitives support for guimauvedigital/zodable.
Author-email: Nathan Fallet <contact@nathanfallet.me>
Requires-Python: >=3.9
Requires-Dist: pydantic
